build/lib/build/lib/python_package_template/__init__.py
build/lib/build/lib/python_package_template/main.py
build/lib/build/lib/python_package_template/version.py
build/lib/build/lib/python_package_template/src/classname.py
build/lib/build/lib/tests/test_sample.py
build/lib/python_package_template/__init__.py
build/lib/python_package_template/main.py
build/lib/python_package_template/version.py
build/lib/python_package_template/src/classname.py
build/lib/tests/test_sample.py
python_package_template/__init__.py
python_package_template/main.py
python_package_template/version.py
python_package_template/src/classname.py
tests/test_sample.py
python_package_template_mldxo-0.1.0.dist-info/LICENSE
python_package_template_mldxo-0.1.0.dist-info/METADATA
python_package_template_mldxo-0.1.0.dist-info/WHEEL
python_package_template_mldxo-0.1.0.dist-info/entry_points.txt
python_package_template_mldxo-0.1.0.dist-info/top_level.txt
python_package_template_mldxo-0.1.0.dist-info/RECORD
