Metadata-Version: 2.1
Name: python-package-template-mldxo
Version: 0.1.0
Summary: Python Package Template Description
Author-email: mldxo <miloszmaculewicz@gmail.com>
Project-URL: Homepage, https://github.com/mldxo/python-package-template
Project-URL: Issues, https://github.com/mldxo/python-package-template/issues
Classifier: Programming Language :: Python :: 3
Classifier: License :: OSI Approved :: MIT License
Classifier: Operating System :: OS Independent
Requires-Python: >=3.8
License-File: LICENSE
